[
  {
    "id": 1,
    "name": "Plaza Mayor de Madrid",
    "description": "Mercado y historia",
    "img": "plazamayor"
  },
  {
    "id": 2,
    "name": "Museo del Prado",
    "description": "Museo",
    "img": "prado"
  },
  {
    "id": 3,
    "name": "Parque del Retiro de Madrid",
    "description": "Parque",
    "img": "retiro"
  },
  {
    "id": 4,
    "name": "Museo Nacional Centro de Arte Reina Sofía",
    "description": "Museo y arquitectura",
    "img": "reinasofia"
  },
  {
    "id": 5,
    "name": "Palacio Real de Madrid",
    "description": "Palacio y arquitectura",
    "img": "palacio"
  },
  {
    "id": 6,
    "name": "Museo Thyssen-Bornemisza",
    "description": "Museo",
    "img": "thyssen"
  }
]
